{"18":{"device":"daemon","Name":"CfNegBoulang_18","TYPE":"historique","DATA":{"23":41719,"11":35643,"14":4470,"4":2256,"15":510,"17":1499,"24":300,"total":86397,"cout":5.23},"score":0.4125},"19":{"device":"daemon","Name":"CfCrermerie_19","TYPE":"historique","DATA":{"11":49673,"22":7829,"14":7560,"23":21337,"total":86399,"cout":7.65},"score":0.5749},"20":{"device":"daemon","Name":"CfNegSSol_20","TYPE":"historique","DATA":{"23":80007,"14":2429,"4":2370,"15":1021,"11":571,"total":86398,"cout":28.72},"score":0.0066},"22":{"device":"daemon","Name":"CfFEtLegume_22","TYPE":"historique","DATA":{"11":59426,"14":8160,"22":18812,"total":86398,"cout":7.04},"score":0.6878},"23":{"device":"daemon","Name":"CfNegDrive_23","TYPE":"historique","DATA":{"0":29379,"11":50930,"14":4049,"4":2040,"total":86398,"cout":2.89},"score":0.5895},"25":{"device":"daemon","Name":"LaitFrais_25","TYPE":"historique","DATA":{"11":60151,"23":18327,"14":7920,"total":86398,"cout":0.46},"score":0.6962},"26":{"device":"daemon","Name":"CharcutFe_26","TYPE":"historique","DATA":{"11":64524,"23":13168,"14":8646,"24":59,"total":86397,"cout":1.14},"score":0.7468},"27":{"device":"daemon","Name":"CharcutFe_27","TYPE":"historique","DATA":{"11":65276,"23":10084,"14":10799,"6":239,"total":86398,"cout":0.74},"score":0.7555},"28":{"device":"daemon","Name":"Salade_28","TYPE":"historique","DATA":{"11":63447,"23":14582,"14":8159,"24":210,"total":86398,"cout":0.34},"score":0.7344},"30":{"device":"daemon","Name":"TraiteurLs_30","TYPE":"historique","DATA":{"1":86400,"total":86400,"cout":2.95},"score":0.0},"34":{"device":"daemon","Name":"TgCharcut_34","TYPE":"historique","DATA":{"14":86400,"total":86400,"cout":2.09},"score":0.0},"42":{"device":"daemon","Name":"TgVolaille_42","TYPE":"historique","DATA":{"23":86400,"total":86400,"cout":2.09},"score":0.0},"43":{"device":"daemon","Name":"VolailleLs_43","TYPE":"historique","DATA":{"11":67542,"23":10309,"14":6899,"22":1648,"total":86398,"cout":0.66},"score":0.7818},"46":{"device":"daemon","Name":"TgVolaille_46","TYPE":"historique","DATA":{"11":34485,"23":51914,"total":86399,"cout":1.25},"score":0.3991},"48":{"device":"daemon","Name":"BouchTrad_48","TYPE":"historique","DATA":{"11":66567,"23":10171,"14":9660,"total":86398,"cout":0.52},"score":0.7705},"49":{"device":"daemon","Name":"CharcutTrad_49","TYPE":"historique","DATA":{"11":57207,"23":19381,"14":9811,"total":86399,"cout":0.77},"score":0.6621},"50":{"device":"daemon","Name":"CharcutTrad_50","TYPE":"historique","DATA":{"11":50756,"23":26222,"14":9420,"total":86398,"cout":0.46},"score":0.5875},"51":{"device":"daemon","Name":"CharcutTrad_51","TYPE":"historique","DATA":{"23":75989,"14":10410,"total":86399,"cout":1.11},"score":0.0},"52":{"device":"daemon","Name":"CaveJambon_52","TYPE":"historique","DATA":{"11":69751,"23":8638,"14":7889,"24":120,"total":86398,"cout":0.13},"score":0.8073},"53":{"device":"daemon","Name":"CaveFromage_53","TYPE":"historique","DATA":{"11":66081,"23":12428,"14":7890,"total":86399,"cout":0.35},"score":0.7648},"54":{"device":"daemon","Name":"CharcutFe_54","TYPE":"historique","DATA":{"23":86400,"total":86400,"cout":3.01},"score":0.0},"57":{"device":"daemon","Name":"CfPoisson_57","TYPE":"historique","DATA":{"0":43190,"11":31781,"14":11099,"4":238,"15":90,"total":86398,"cout":6.95},"score":0.3678},"58":{"device":"daemon","Name":"LaboPoisson_58","TYPE":"historique","DATA":{"11":20547,"0":49593,"14":16259,"total":86399,"cout":7.0},"score":0.2378},"59":{"device":"daemon","Name":"TgFromage_59","TYPE":"historique","DATA":{"11":49413,"23":24924,"14":12061,"total":86398,"cout":0.89},"score":0.5719},"60":{"device":"daemon","Name":"FromageLs_60","TYPE":"historique","DATA":{"11":65823,"22":6655,"23":6660,"14":7050,"1":119,"6":89,"total":86396,"cout":0.72},"score":0.7619},"61":{"device":"daemon","Name":"FromageLs_61","TYPE":"historique","DATA":{"23":86400,"total":86400,"cout":4.54},"score":0.0},"62":{"device":"daemon","Name":"FromageLs_62","TYPE":"historique","DATA":{"23":86400,"total":86400,"cout":4.54},"score":0.0},"63":{"device":"daemon","Name":"TgFromage_63","TYPE":"historique","DATA":{"23":86400,"total":86400,"cout":2.09},"score":0.0},"65":{"device":"daemon","Name":"YahourtLs_65","TYPE":"historique","DATA":{"23":86400,"total":86400,"cout":4.54},"score":0.0},"66":{"device":"daemon","Name":"YahourtLs_66","TYPE":"historique","DATA":{"23":86400,"total":86400,"cout":4.54},"score":0.0},"69":{"device":"daemon","Name":"YahourtLs_69","TYPE":"historique","DATA":{"23":86400,"total":86400,"cout":3.01},"score":0.0},"70":{"device":"daemon","Name":"SurgPorte_70","TYPE":"historique","DATA":{"23":84029,"14":780,"1":689,"4":570,"15":329,"total":86397,"cout":5.47},"score":0.0},"71":{"device":"daemon","Name":"SurgPorte_71","TYPE":"historique","DATA":{"23":45850,"11":38508,"14":1470,"4":570,"total":86398,"cout":3.03},"score":0.4457},"72":{"device":"daemon","Name":"SurgPorte_72","TYPE":"historique","DATA":{"23":65430,"11":14878,"14":1140,"1":3659,"4":600,"15":690,"total":86397,"cout":3.6},"score":0.1722},"73":{"device":"daemon","Name":"SurgPorte_73","TYPE":"historique","DATA":{"23":80309,"14":1140,"1":3839,"4":420,"15":690,"total":86398,"cout":22.61},"score":0.0},"74":{"device":"daemon","Name":"SurgPorte_74","TYPE":"historique","DATA":{"11":57775,"22":23013,"14":2250,"4":1320,"23":1680,"15":360,"total":86398,"cout":1.81},"score":0.6687},"75":{"device":"daemon","Name":"SurgPorte_75","TYPE":"historique","DATA":{"23":63291,"11":19178,"14":1500,"1":749,"4":1680,"total":86398,"cout":4.26},"score":0.222},"76":{"device":"daemon","Name":"TgBacSurg_76","TYPE":"historique","DATA":{"11":45660,"23":38099,"14":1680,"4":959,"total":86398,"cout":1.06},"score":0.5285},"77":{"device":"daemon","Name":"BacSurg_77","TYPE":"historique","DATA":{"11":46291,"23":36537,"14":2820,"4":600,"15":150,"total":86398,"cout":2.01},"score":0.5358},"78":{"device":"daemon","Name":"TgBacSurg_78","TYPE":"historique","DATA":{"11":58888,"23":24871,"14":1680,"4":689,"15":269,"total":86397,"cout":0.72},"score":0.6816},"79":{"device":"daemon","Name":"TourBoucherie_79","TYPE":"historique","DATA":{"11":42179,"14":11016,"23":33204,"total":86399,"cout":0.65},"score":0.4882},"80":{"device":"daemon","Name":"TraiteurSv_80","TYPE":"historique","DATA":{"11":64428,"23":11105,"14":10716,"24":150,"total":86399,"cout":0.39},"score":0.7457},"81":{"device":"daemon","Name":"TgTraiteurSv_81","TYPE":"historique","DATA":{"11":54394,"23":20545,"14":10799,"18":659,"total":86397,"cout":0.44},"score":0.6296},"82":{"device":"daemon","Name":"TraiteurSv_82","TYPE":"historique","DATA":{"23":20626,"11":55027,"14":10416,"24":330,"total":86399,"cout":0.56},"score":0.6369},"83":{"device":"daemon","Name":"PoissonSv_83","TYPE":"historique","DATA":{"11":44638,"23":32131,"14":9630,"total":86399,"cout":0.61},"score":0.5166},"102":{"device":"daemon","Name":"SalleDMachine_102","TYPE":"historique","DATA":{"11":24081,"0":52748,"14":9569,"total":86398,"cout":0.0},"score":0.2787}}