{"1":{"device":"daemon","Name":"SasSurgeles_1","TYPE":"historique","DATA":{"11":4451,"23":16333,"10":65028,"14":406,"15":180,"total":86398,"cout":14.51},"score":0.0515},"2":{"device":"daemon","Name":"SasFrais_2","TYPE":"historique","DATA":{"23":36535,"11":39335,"18":359,"14":10169,"total":86398,"cout":29.35},"score":0.4553},"3":{"device":"daemon","Name":"CfDrive_3","TYPE":"historique","DATA":{"11":51531,"23":23355,"14":10280,"18":1232,"total":86398,"cout":6.72},"score":0.5964},"4":{"device":"daemon","Name":"CfSurgeles_4","TYPE":"historique","DATA":{"23":45834,"11":36588,"14":1956,"4":1379,"15":641,"total":86398,"cout":18.97},"score":0.4235},"5":{"device":"daemon","Name":"CfSurgeles_5","TYPE":"historique","DATA":{"23":81831,"14":2982,"4":1043,"15":542,"total":86398,"cout":21.9},"score":0.0},"6":{"device":"daemon","Name":"CfFruitLeg_6","TYPE":"historique","DATA":{"11":70121,"0":5936,"14":8478,"23":1863,"total":86398,"cout":5.39},"score":0.8116},"7":{"device":"daemon","Name":"CfCremerie_7","TYPE":"historique","DATA":{"14":12389,"23":13526,"11":60483,"total":86398,"cout":5.0},"score":0.7001},"8":{"device":"daemon","Name":"CfCharcut_8","TYPE":"historique","DATA":{"14":12133,"23":17536,"11":56730,"total":86399,"cout":5.72},"score":0.6566},"10":{"device":"daemon","Name":"CfTraitTrad_10","TYPE":"historique","DATA":{"11":61437,"0":12812,"14":11902,"23":247,"total":86398,"cout":4.81},"score":0.7111},"11":{"device":"daemon","Name":"CfFe_11","TYPE":"historique","DATA":{"11":64333,"0":7554,"14":14511,"total":86398,"cout":4.25},"score":0.7446},"12":{"device":"daemon","Name":"LaboPoisson_12","TYPE":"historique","DATA":{"22":1648,"23":6489,"11":68244,"14":10017,"total":86398,"cout":1.79},"score":0.7899},"13":{"device":"daemon","Name":"CfPoisson_13","TYPE":"historique","DATA":{"14":16074,"0":14838,"11":55486,"total":86398,"cout":5.31},"score":0.6422},"15":{"device":"daemon","Name":"SurgPorte_15","TYPE":"historique","DATA":{"11":49227,"23":34448,"14":2003,"4":630,"15":90,"total":86398,"cout":1.36},"score":0.5698},"16":{"device":"daemon","Name":"SurgPorte_16","TYPE":"historique","DATA":{"11":45686,"23":37902,"14":1643,"1":357,"4":810,"total":86398,"cout":1.49},"score":0.5288},"17":{"device":"daemon","Name":"SurgPorte_17","TYPE":"historique","DATA":{"11":28775,"23":54451,"14":2393,"4":599,"15":180,"total":86398,"cout":2.2},"score":0.3331},"18":{"device":"daemon","Name":"SurgPorte_18","TYPE":"historique","DATA":{"11":13868,"23":70948,"14":742,"4":630,"15":209,"total":86397,"cout":0.98},"score":0.1605},"19":{"device":"daemon","Name":"SurgPorte_19","TYPE":"historique","DATA":{"23":46917,"11":38612,"14":870,"total":86399,"cout":1.75},"score":0.4469},"20":{"device":"daemon","Name":"SurgPorte_20","TYPE":"historique","DATA":{"11":42264,"23":43153,"14":981,"total":86398,"cout":1.62},"score":0.4892},"21":{"device":"daemon","Name":"SurgPorte_21","TYPE":"historique","DATA":{"11":32261,"23":52278,"14":1122,"4":628,"15":109,"total":86398,"cout":1.98},"score":0.3734},"22":{"device":"daemon","Name":"TgSurgP_22","TYPE":"historique","DATA":{"23":83497,"14":2152,"4":600,"15":148,"total":86397,"cout":1.02},"score":0.0},"25":{"device":"daemon","Name":"TgBacSurg_25","TYPE":"historique","DATA":{"11":59543,"23":22356,"14":3003,"4":1406,"15":90,"total":86398,"cout":0.56},"score":0.6892},"26":{"device":"daemon","Name":"BacSurg_26","TYPE":"historique","DATA":{"23":28972,"11":50582,"14":2083,"1":3976,"15":364,"4":420,"total":86397,"cout":1.45},"score":0.5855},"27":{"device":"daemon","Name":"BacSurg_27","TYPE":"historique","DATA":{"23":33981,"11":45938,"14":5850,"4":630,"total":86399,"cout":1.63},"score":0.5317},"30":{"device":"daemon","Name":"Fe_30","TYPE":"historique","DATA":{"14":18899,"11":63837,"0":3663,"total":86399,"cout":0.79},"score":0.7389},"31":{"device":"daemon","Name":"Fe_31","TYPE":"historique","DATA":{"23":42283,"11":33452,"24":30,"14":10634,"total":86399,"cout":0.84},"score":0.3872},"32":{"device":"daemon","Name":"Fe_32","TYPE":"historique","DATA":{"23":30673,"11":45030,"14":10695,"total":86398,"cout":0.62},"score":0.5212},"33":{"device":"daemon","Name":"BouchTrad_33","TYPE":"historique","DATA":{"11":52154,"23":24843,"14":9402,"total":86399,"cout":0.39},"score":0.6036},"34":{"device":"daemon","Name":"BouchTrad_34","TYPE":"historique","DATA":{"11":60296,"23":16690,"14":9412,"total":86398,"cout":0.29},"score":0.6979},"35":{"device":"daemon","Name":"BouchTrad_35","TYPE":"historique","DATA":{"11":41327,"23":35630,"14":9442,"total":86399,"cout":0.51},"score":0.4783},"36":{"device":"daemon","Name":"CfBoulang_36","TYPE":"historique","DATA":{"14":11719,"23":38814,"11":35866,"total":86399,"cout":2.67},"score":0.4151},"37":{"device":"daemon","Name":"CfSurgBoulang_37","TYPE":"historique","DATA":{"23":41411,"11":41181,"14":3536,"4":270,"total":86398,"cout":3.57},"score":0.4766},"38":{"device":"daemon","Name":"CharcutTrad_38","TYPE":"historique","DATA":{"11":64299,"23":10267,"14":11833,"total":86399,"cout":0.25},"score":0.7442},"39":{"device":"daemon","Name":"CharcutTrad_39","TYPE":"historique","DATA":{"11":52463,"23":22142,"14":10917,"1":877,"total":86399,"cout":0.53},"score":0.6072},"40":{"device":"daemon","Name":"CharcutTrad_40","TYPE":"historique","DATA":{"11":58491,"23":16102,"14":10928,"1":877,"total":86398,"cout":0.44},"score":0.677},"41":{"device":"daemon","Name":"TgFrais_41","TYPE":"historique","DATA":{"23":11255,"11":66713,"14":8431,"total":86399,"cout":0.44},"score":0.7722},"42":{"device":"daemon","Name":"BouchLs_42","TYPE":"historique","DATA":{"11":64698,"23":10450,"14":11251,"total":86399,"cout":0.58},"score":0.7488},"43":{"device":"daemon","Name":"BouchLs_43","TYPE":"historique","DATA":{"11":62925,"23":12172,"14":11302,"total":86399,"cout":0.96},"score":0.7283},"44":{"device":"daemon","Name":"VolailleLs_44","TYPE":"historique","DATA":{"11":64338,"23":10716,"14":11345,"total":86399,"cout":0.9},"score":0.7447},"45":{"device":"daemon","Name":"VolailleLs_45","TYPE":"historique","DATA":{"11":63348,"23":11748,"14":11302,"total":86398,"cout":0.94},"score":0.7332},"46":{"device":"daemon","Name":"TgFrais_46","TYPE":"historique","DATA":{"11":60907,"23":14177,"14":11315,"total":86399,"cout":0.57},"score":0.705},"47":{"device":"daemon","Name":"TraiteurLs_47","TYPE":"historique","DATA":{"23":33334,"11":42240,"14":10825,"total":86399,"cout":1.35},"score":0.4889},"48":{"device":"daemon","Name":"TraiteurLs_48","TYPE":"historique","DATA":{"11":68187,"23":7473,"14":10738,"total":86398,"cout":0.84},"score":0.7892},"49":{"device":"daemon","Name":"TraiteurLs_49","TYPE":"historique","DATA":{"23":7037,"11":68580,"14":10781,"total":86398,"cout":0.82},"score":0.7938},"50":{"device":"daemon","Name":"TraiteurLs_50","TYPE":"historique","DATA":{"11":64960,"23":10724,"14":10714,"total":86398,"cout":0.99},"score":0.7519},"51":{"device":"daemon","Name":"LaboBouch_51","TYPE":"historique","DATA":{"11":48147,"22":3777,"23":24435,"14":10039,"total":86398,"cout":17.06},"score":0.5573},"52":{"device":"daemon","Name":"CfCarcasse_52","TYPE":"historique","DATA":{"23":32755,"18":448,"14":12587,"11":40608,"total":86398,"cout":6.88},"score":0.47},"53":{"device":"daemon","Name":"CfProdF_53","TYPE":"historique","DATA":{"23":11366,"11":62907,"14":12125,"total":86398,"cout":3.53},"score":0.7281},"54":{"device":"daemon","Name":"CfBarquette_54","TYPE":"historique","DATA":{"11":71286,"23":6661,"14":8451,"total":86398,"cout":2.91},"score":0.8251},"55":{"device":"daemon","Name":"Saurisserie_55","TYPE":"historique","DATA":{"23":16352,"11":59210,"14":10837,"total":86399,"cout":0.83},"score":0.6853},"56":{"device":"daemon","Name":"Saurisserie_56","TYPE":"historique","DATA":{"11":65868,"23":9718,"14":10812,"total":86398,"cout":0.63},"score":0.7624},"57":{"device":"daemon","Name":"Charcuterie_57","TYPE":"historique","DATA":{"11":64907,"23":10109,"14":11383,"total":86399,"cout":0.66},"score":0.7512},"58":{"device":"daemon","Name":"Charcuterie_58","TYPE":"historique","DATA":{"11":64574,"23":10387,"14":11437,"total":86398,"cout":0.67},"score":0.7474},"59":{"device":"daemon","Name":"Charcuterie_59","TYPE":"historique","DATA":{"11":64020,"23":10979,"14":11399,"total":86398,"cout":1.03},"score":0.741},"60":{"device":"daemon","Name":"Charcuterie_60","TYPE":"historique","DATA":{"23":15611,"11":59528,"14":11260,"total":86399,"cout":1.24},"score":0.689},"61":{"device":"daemon","Name":"CfSuif_61","TYPE":"historique","DATA":{"11":35424,"23":38590,"14":12384,"total":86398,"cout":9.83},"score":0.41},"62":{"device":"daemon","Name":"4eGamme_62","TYPE":"historique","DATA":{"11":63030,"23":11843,"14":11525,"total":86398,"cout":0.72},"score":0.7295},"63":{"device":"daemon","Name":"4eGamme_63","TYPE":"historique","DATA":{"11":58820,"23":15982,"14":11597,"total":86399,"cout":0.84},"score":0.6808},"64":{"device":"daemon","Name":"4eGamme_64","TYPE":"historique","DATA":{"11":63691,"23":11244,"14":11463,"total":86398,"cout":1.05},"score":0.7372},"65":{"device":"daemon","Name":"TgFrais_65","TYPE":"historique","DATA":{"14":10757,"23":12991,"11":62650,"total":86398,"cout":0.31},"score":0.7251},"66":{"device":"daemon","Name":"FromageLs_66","TYPE":"historique","DATA":{"11":70049,"23":5593,"14":10756,"total":86398,"cout":0.5},"score":0.8108},"67":{"device":"daemon","Name":"FromageLs_67","TYPE":"historique","DATA":{"11":68985,"23":6761,"14":10652,"total":86398,"cout":0.8},"score":0.7985},"68":{"device":"daemon","Name":"FromageLs_68","TYPE":"historique","DATA":{"11":66256,"23":9529,"14":10614,"total":86399,"cout":0.93},"score":0.7669},"69":{"device":"daemon","Name":"FromageLs_69","TYPE":"historique","DATA":{"11":69449,"23":6413,"14":10537,"total":86399,"cout":0.78},"score":0.8038},"70":{"device":"daemon","Name":"TgFrais_70","TYPE":"historique","DATA":{"23":9173,"11":69161,"14":8064,"total":86398,"cout":0.39},"score":0.8005},"71":{"device":"daemon","Name":"UltraFrais_71","TYPE":"historique","DATA":{"14":9982,"23":8050,"11":68367,"total":86399,"cout":0.83},"score":0.7913},"72":{"device":"daemon","Name":"UltraFrais_72","TYPE":"historique","DATA":{"14":10316,"23":6111,"11":69971,"total":86398,"cout":0.76},"score":0.8099},"73":{"device":"daemon","Name":"UltraFrais_73","TYPE":"historique","DATA":{"14":10753,"23":7303,"11":68343,"total":86399,"cout":0.55},"score":0.791},"74":{"device":"daemon","Name":"UltraFrais_74","TYPE":"historique","DATA":{"14":10699,"23":6447,"11":69253,"total":86399,"cout":0.79},"score":0.8015},"75":{"device":"daemon","Name":"TgFrais_75","TYPE":"historique","DATA":{"11":30298,"23":45324,"14":10776,"total":86398,"cout":1.26},"score":0.3507},"76":{"device":"daemon","Name":"UltraFrais_76","TYPE":"historique","DATA":{"11":69180,"23":7518,"14":9700,"total":86398,"cout":0.53},"score":0.8007},"77":{"device":"daemon","Name":"UltraFrais_77","TYPE":"historique","DATA":{"11":69404,"23":7596,"14":9399,"total":86399,"cout":0.79},"score":0.8033},"78":{"device":"daemon","Name":"UltraFrais_78","TYPE":"historique","DATA":{"11":70215,"23":6600,"14":9583,"total":86398,"cout":0.75},"score":0.8127},"79":{"device":"daemon","Name":"UltraFrais_79","TYPE":"historique","DATA":{"11":68073,"23":8562,"14":9764,"total":86399,"cout":0.85},"score":0.7879},"80":{"device":"daemon","Name":"TgFrais_80","TYPE":"historique","DATA":{"23":37627,"11":37803,"14":10938,"24":29,"total":86397,"cout":1.09},"score":0.4375},"81":{"device":"daemon","Name":"BacFe_81","TYPE":"historique","DATA":{"11":58406,"23":18330,"14":9663,"total":86399,"cout":0.48},"score":0.676},"82":{"device":"daemon","Name":"TgBacFe_82","TYPE":"historique","DATA":{"11":60623,"23":16038,"14":9737,"total":86398,"cout":0.1},"score":0.7017},"83":{"device":"daemon","Name":"BacFe_83","TYPE":"historique","DATA":{"14":10763,"23":18117,"11":57518,"total":86398,"cout":0.33},"score":0.6657},"84":{"device":"daemon","Name":"TgBacFe_84","TYPE":"historique","DATA":{"14":10781,"23":18122,"11":57495,"total":86398,"cout":0.11},"score":0.6655},"102":{"device":"daemon","Name":"ClimSdm_102","TYPE":"historique","DATA":{"0":78900,"14":7499,"total":86399,"cout":0.0},"score":0.0},"0":{"device":"daemon","Name":"LaboCharcut_0","TYPE":"historique","DATA":{"23":33575,"11":47775,"14":4902,"10":147,"total":86399,"cout":0.25},"score":0.553}}